{
	"name": "AlvoCanhaoD",
	"plugin-id": "Sprite",
	"sid": 403772203478438,
	"isGlobal": false,
	"editorNewInstanceIsReplica": true,
	"instanceVariables": [],
	"behaviorTypes": [],
	"effectTypes": [],
	"animations": {
		"items": [
			{
				"frames": [
					{
						"width": 32,
						"height": 32,
						"originX": 0,
						"originY": 0,
						"originalSource": "",
						"exportFormat": "lossless",
						"exportQuality": 0.8,
						"fileType": "image/png",
						"imageSpriteId": 9672826,
						"useCollisionPoly": true,
						"duration": 1,
						"tag": ""
					}
				],
				"sid": 695265961413925,
				"name": "Animation 1",
				"isLooping": false,
				"isPingPong": false,
				"repeatCount": 1,
				"repeatTo": 0,
				"speed": 5
			}
		],
		"subfolders": []
	}
}